suta_ble_bed/__init__.py
suta_ble_bed/__main__.py
suta_ble_bed/cli.py
suta_ble_bed/suta_ble_bed.py
suta_ble_bed/suta_ble_bed_controller.py
suta_ble_bed/suta_ble_consts.py
suta_ble_bed/suta_ble_scanner.py
suta_ble_bed-0.3.6.dist-info/LICENSE
suta_ble_bed-0.3.6.dist-info/METADATA
suta_ble_bed-0.3.6.dist-info/WHEEL
suta_ble_bed-0.3.6.dist-info/entry_points.txt
suta_ble_bed-0.3.6.dist-info/top_level.txt
suta_ble_bed-0.3.6.dist-info/RECORD
