Metadata-Version: 2.1
Name: suta_ble_bed
Version: 0.3.6
Summary: Handle BLE communications for a SUTA bed frame such as the i500 or i800.
Home-page: https://github.com/sredman/suta_ble_bed
Author: Simon Redman
Author-email: simon@ergotech.com
License: MIT license
Keywords: SUTA,sleepmotion,i500,i900,i200
Classifier: Development Status :: 2 - Pre-Alpha
Classifier: Intended Audience :: Developers
Classifier: License :: OSI Approved :: MIT License
Classifier: Natural Language :: English
Classifier: Programming Language :: Python :: 3
Classifier: Programming Language :: Python :: 3.6
Classifier: Programming Language :: Python :: 3.7
Classifier: Programming Language :: Python :: 3.8
Requires-Python: >=3.6
License-File: LICENSE
Requires-Dist: bleak >=0.19.5
Requires-Dist: bleak-retry-connector >=3.0.0
